QDA.py
QDA-0.0.2.dist-info/LICENSE.txt
QDA-0.0.2.dist-info/METADATA
QDA-0.0.2.dist-info/WHEEL
QDA-0.0.2.dist-info/top_level.txt
QDA-0.0.2.dist-info/RECORD
