Metadata-Version: 2.1
Name: QDA
Version: 0.0.2
Summary: A tool for quantitatively measuring the discursive similarity between bodies of text.
Home-page: https://github.com/metalcorebear/Quantitative-Discursive-Analysis
Author: metalcorebear
Author-email: mark.mbailey@gmail.com
License: UNKNOWN
Platform: UNKNOWN
Classifier: Programming Language :: Python :: 3.9
Classifier: License :: OSI Approved :: MIT License
Classifier: Operating System :: OS Independent
Requires-Python: >=2.7
License-File: LICENSE.txt
Requires-Dist: networkx
Requires-Dist: textblob
Requires-Dist: numpy
